Metadata-Version: 2.1
Name: bilibili-api
Version: 9.1.0
Summary: 哔哩哔哩的各种 API 调用便捷整合（视频、动态、直播等），另外附加一些常用的功能。
Home-page: https://github.com/MoyuScript/bilibili-api
Author: MoyuScript
License: GPLv3+
Keywords: bilibili,api,spider
Platform: UNKNOWN
Classifier: License :: OSI Approved :: GNU General Public License v3 or later (GPLv3+)
Classifier: Natural Language :: Chinese (Simplified)
Classifier: Programming Language :: Python :: 3.8
Classifier: Programming Language :: Python :: 3.9
Requires-Python: >=3.8
